{
  "s": true,
  "d": [
    {
      "id": 16001
    },
    {
      "id": 25100
    },
    {
      "id": 60955
    },
    {
      "id": 68856
    },
    {
      "id": 36901
    },
    {
      "id": 77113
    },
    {
      "id": 16202
    },
    {
      "id": 20155
    },
    {
      "id": 15802
    },
    {
      "id": 16506
    },
    {
      "id": 33353
    },
    {
      "id": 22102
    },
    {
      "id": 35000
    },
    {
      "id": 224
    },
    {
      "id": 77254
    },
    {
      "id": 223
    },
    {
      "id": 17401
    },
    {
      "id": 10101
    },
    {
      "id": 17800
    },
    {
      "id": 17301
    },
    {
      "id": 225
    },
    {
      "id": 78471
    },
    {
      "id": 8651
    },
    {
      "id": 226
    },
    {
      "id": 10100
    },
    {
      "id": 16758
    },
    {
      "id": 227
    },
    {
      "id": 228
    },
    {
      "id": 20801
    },
    {
      "id": 229
    },
    {
      "id": 27452
    },
    {
      "id": 17300
    },
    {
      "id": 20503
    },
    {
      "id": 28801
    },
    {
      "id": 68357
    },
    {
      "id": 76002
    },
    {
      "id": 29500
    },
    {
      "id": 65704
    },
    {
      "id": 23703
    },
    {
      "id": 75857
    },
    {
      "id": 58005
    },
    {
      "id": 62000
    },
    {
      "id": 57205
    },
    {
      "id": 48652
    },
    {
      "id": 50202
    },
    {
      "id": 66050
    },
    {
      "id": 76153
    },
    {
      "id": 54609
    },
    {
      "id": 63870
    },
    {
      "id": 44851
    },
    {
      "id": 43550
    },
    {
      "id": 42450
    },
    {
      "id": 56100
    },
    {
      "id": 53101
    },
    {
      "id": 78354
    },
    {
      "id": 44305
    },
    {
      "id": 52300
    },
    {
      "id": 64066
    },
    {
      "id": 38008
    },
    {
      "id": 53102
    },
    {
      "id": 29760
    },
    {
      "id": 59257
    },
    {
      "id": 57405
    },
    {
      "id": 63350
    },
    {
      "id": 57469
    },
    {
      "id": 76759
    },
    {
      "id": 58800
    },
    {
      "id": 64952
    },
    {
      "id": 53902
    },
    {
      "id": 54507
    },
    {
      "id": 56700
    },
    {
      "id": 78172
    },
    {
      "id": 60250
    },
    {
      "id": 62653
    },
    {
      "id": 58400
    },
    {
      "id": 32806
    },
    {
      "id": 73500
    },
    {
      "id": 32751
    },
    {
      "id": 59803
    },
    {
      "id": 64753
    },
    {
      "id": 52750
    },
    {
      "id": 58967
    },
    {
      "id": 69700
    },
    {
      "id": 60803
    },
    {
      "id": 58908
    },
    {
      "id": 30203
    },
    {
      "id": 43051
    },
    {
      "id": 51855
    },
    {
      "id": 47202
    },
    {
      "id": 50855
    },
    {
      "id": 57101
    },
    {
      "id": 27100
    },
    {
      "id": 57506
    },
    {
      "id": 73201
    },
    {
      "id": 56457
    },
    {
      "id": 69253
    },
    {
      "id": 65157
    },
    {
      "id": 68500
    },
    {
      "id": 61601
    },
    {
      "id": 78177
    }
  ],
  "sp": {
    "page": 14,
    "sort": null,
    "pageSize": 100,
    "pageCount": 59,
    "rowCount": 5893,
    "start": 1300,
    "limit": null
  }
}